pyapollo/__init__.py
pyapollo/apollo_client.py
pyapollo/async_apollo_client.py
pyapollo/constant.py
pyapollo/format_parser.py
pyapollo/parser_selector.py
pyapollo/strengthen_apollo_client.py
strengthen_apollo_client-1.0.3.dist-info/LICENSE
strengthen_apollo_client-1.0.3.dist-info/METADATA
strengthen_apollo_client-1.0.3.dist-info/WHEEL
strengthen_apollo_client-1.0.3.dist-info/top_level.txt
strengthen_apollo_client-1.0.3.dist-info/RECORD
