Metadata-Version: 2.1
Name: strengthen-apollo-client
Version: 1.0.3
Summary: Python version client based on Apollo
Home-page: https://github.com/Darr-en1/pyapollo
Author: darr_en1
Author-email: zhouttt1995@gmail.com
License: UNKNOWN
Platform: any
Classifier: Programming Language :: Python :: 3.6
License-File: LICENSE
Requires-Dist: requests
Requires-Dist: pyyaml
Requires-Dist: aiohttp
